setup.py
Gaussian_binomial/Binomialdistribution.py
Gaussian_binomial/Gaussiandistribution.py
Gaussian_binomial/Generaldistribution.py
Gaussian_binomial/__init__.py
Gaussian_binomial.egg-info/PKG-INFO
Gaussian_binomial.egg-info/SOURCES.txt
Gaussian_binomial.egg-info/dependency_links.txt
Gaussian_binomial.egg-info/not-zip-safe
Gaussian_binomial.egg-info/top_level.txt