Metadata-Version: 1.0
Name: Gaussian-binomial
Version: 0.1
Summary: Gaussian and Binomial distributions
Home-page: UNKNOWN
Author: Dheeraj Mitra
Author-email: dheerajmitra17@gmail.com
License: UNKNOWN
Platform: UNKNOWN
